bootstrap.py
buildout.cfg
setup.py
src/__init__.py
src/archetypes/__init__.py
src/archetypes.fieldtraverser.egg-info/PKG-INFO
src/archetypes.fieldtraverser.egg-info/SOURCES.txt
src/archetypes.fieldtraverser.egg-info/dependency_links.txt
src/archetypes.fieldtraverser.egg-info/entry_points.txt
src/archetypes.fieldtraverser.egg-info/namespace_packages.txt
src/archetypes.fieldtraverser.egg-info/not-zip-safe
src/archetypes.fieldtraverser.egg-info/requires.txt
src/archetypes.fieldtraverser.egg-info/top_level.txt
src/archetypes/fieldtraverser/README.txt
src/archetypes/fieldtraverser/__init__.py
src/archetypes/fieldtraverser/configure.zcml
src/archetypes/fieldtraverser/fieldtraverser-tests.txt
src/archetypes/fieldtraverser/fieldtraverser.py
src/archetypes/fieldtraverser/patch.py
src/archetypes/fieldtraverser/profiles.zcml
src/archetypes/fieldtraverser/profile/skins.xml
src/archetypes/fieldtraverser/skins/fieldtraverser/widget-file-fieldtraverser.pt
src/archetypes/fieldtraverser/skins/fieldtraverser/widget-image-fieldtraverser.pt
src/archetypes/fieldtraverser/skins/fieldtraverser/widget-rich-fieldtraverser.pt
src/archetypes/fieldtraverser/tests/__init__.py
src/archetypes/fieldtraverser/tests/filetest.txt
src/archetypes/fieldtraverser/tests/interact.py
src/archetypes/fieldtraverser/tests/plone.jpg
src/archetypes/fieldtraverser/tests/plone.jpg.CREDITS
src/archetypes/fieldtraverser/tests/test_doctests.py