Metadata-Version: 1.0
Name: archetypes.fieldtraverser
Version: 0.4.4
Summary: Archetypes fieldtraverser
Home-page: http://svn.plone.org/svn/archetypes/archetypes.fieldtraverser
Author: Jens Klein, Johannes Raggam
Author-email: dev@bluedynamics.com
License: GPL
Keywords: archetypes fieldtraverser
Platform: UNKNOWN
Classifier: Development Status :: 4 - Beta
Classifier: Environment :: Web Environment
Classifier: Framework :: Zope2
Classifier: License :: OSI Approved :: GNU General Public License (GPL)
Classifier: Operating System :: OS Independent
Classifier: Programming Language :: Python
Classifier: Topic :: Internet :: WWW/HTTP :: Dynamic Content
